Avenue-0.2.2.dist-info/DESCRIPTION.rst
Avenue-0.2.2.dist-info/METADATA
Avenue-0.2.2.dist-info/RECORD
Avenue-0.2.2.dist-info/WHEEL
Avenue-0.2.2.dist-info/metadata.json
Avenue-0.2.2.dist-info/top_level.txt
avenue/__init__.py
avenue/avenue.py
avenue/processors.py
