Metadata-Version: 2.0
Name: Avenue
Version: 0.2.2
Summary: Avenue: Highway routing.
Home-page: https://github.com/CorverDevelopment/Avenue/
Author: Nils Corver
Author-email: nils@corverdevelopment.nl
License: MIT
Keywords: routing
Platform: UNKNOWN
Classifier: Development Status :: 3 - Alpha
Classifier: Intended Audience :: Developers
Classifier: Natural Language :: English
Classifier: License :: OSI Approved :: MIT License
Classifier: Operating System :: OS Independent
Classifier: Programming Language :: Python
Classifier: Programming Language :: Python :: 2
Classifier: Programming Language :: Python :: 2.7
Classifier: Programming Language :: Python :: 3
Classifier: Programming Language :: Python :: 3.5
Classifier: Programming Language :: Python :: Implementation :: CPython
Classifier: Topic :: Software Development :: Libraries :: Python Modules
Requires-Dist: Pandora (>=0.2.2)
